imapclient/__init__.py
imapclient/config.py
imapclient/datetime_util.py
imapclient/exceptions.py
imapclient/fixed_offset.py
imapclient/imap4.py
imapclient/imap_utf7.py
imapclient/imapclient.py
imapclient/imaplib_ssl_fix.py
imapclient/interact.py
imapclient/livetest.py
imapclient/response_lexer.py
imapclient/response_parser.py
imapclient/response_types.py
imapclient/testable_imapclient.py
imapclient/tls.py
imapclient/typing_imapclient.py
imapclient/util.py
imapclient/version.py
imapclient/__pycache__/__init__.cpython-37.pyc
imapclient/__pycache__/config.cpython-37.pyc
imapclient/__pycache__/datetime_util.cpython-37.pyc
imapclient/__pycache__/exceptions.cpython-37.pyc
imapclient/__pycache__/fixed_offset.cpython-37.pyc
imapclient/__pycache__/imap4.cpython-37.pyc
imapclient/__pycache__/imap_utf7.cpython-37.pyc
imapclient/__pycache__/imapclient.cpython-37.pyc
imapclient/__pycache__/imaplib_ssl_fix.cpython-37.pyc
imapclient/__pycache__/interact.cpython-37.pyc
imapclient/__pycache__/livetest.cpython-37.pyc
imapclient/__pycache__/response_lexer.cpython-37.pyc
imapclient/__pycache__/response_parser.cpython-37.pyc
imapclient/__pycache__/response_types.cpython-37.pyc
imapclient/__pycache__/testable_imapclient.cpython-37.pyc
imapclient/__pycache__/tls.cpython-37.pyc
imapclient/__pycache__/util.cpython-37.pyc
imapclient/__pycache__/version.cpython-37.pyc
imapclient/examples/example.py
imapclient/examples/idle_example.py
imapclient/examples/oauth2_example.py
imapclient/examples/tls_cacert.py
imapclient/examples/tls_no_checks.py
imapclient/examples/__pycache__/example.cpython-37.pyc
imapclient/examples/__pycache__/idle_example.cpython-37.pyc
imapclient/examples/__pycache__/oauth2_example.cpython-37.pyc
imapclient/examples/__pycache__/tls_cacert.cpython-37.pyc
imapclient/examples/__pycache__/tls_no_checks.cpython-37.pyc
imapclient/test/__init__.py
imapclient/test/imapclient_test.py
imapclient/test/test_auth.py
imapclient/test/test_datetime_util.py
IMAPClient-3.0.0.dist-info/AUTHORS.rst
IMAPClient-3.0.0.dist-info/COPYING
IMAPClient-3.0.0.dist-info/METADATA
IMAPClient-3.0.0.dist-info/WHEEL
IMAPClient-3.0.0.dist-info/top_level.txt
IMAPClient-3.0.0.dist-info/RECORD
