Metadata-Version: 2.1
Name: IMAPClient
Version: 3.0.0
Summary: Easy-to-use, Pythonic and complete IMAP client library
Home-page: https://github.com/mjs/imapclient/
Author: Menno Finlay-Smits
Author-email: inbox@menno.io
Maintainer: IMAPClient Maintainers
Maintainer-email: imapclient@groups.io
License: 3-Clause BSD License
Keywords: imap client email mail
Classifier: Development Status :: 5 - Production/Stable
Classifier: Intended Audience :: Developers
Classifier: License :: OSI Approved :: BSD License
Classifier: Operating System :: OS Independent
Classifier: Natural Language :: English
Classifier: Programming Language :: Python
Classifier: Programming Language :: Python :: 3
Classifier: Topic :: Communications :: Email :: Post-Office :: IMAP
Classifier: Topic :: Internet
Classifier: Topic :: Software Development :: Libraries :: Python Modules
Classifier: Topic :: System :: Networking
Requires-Python: >=3.7.0
License-File: COPYING
License-File: AUTHORS.rst
Provides-Extra: doc
Requires-Dist: sphinx; extra == "doc"
